seistools/__init__.py
seistools/reader.py
seistools/sampleconversion.cpython-39-darwin.so
seismic_toolbox-0.0.1.dist-info/LICENSE
seismic_toolbox-0.0.1.dist-info/METADATA
seismic_toolbox-0.0.1.dist-info/WHEEL
seismic_toolbox-0.0.1.dist-info/top_level.txt
seismic_toolbox-0.0.1.dist-info/RECORD
