Metadata-Version: 2.1
Name: seismic-toolbox
Version: 0.0.1
Summary: Seismic toolbox for numpy
Home-page: https://github.com/oliche/seismic-toolbox
Author: Olivier Winter
License: UNKNOWN
Project-URL: Bug Tracker, https://github.com/oliche/seismic-toolbox/issues
Platform: UNKNOWN
Classifier: Programming Language :: Python :: 3
Classifier: License :: OSI Approved :: MIT License
Classifier: Operating System :: OS Independent
Requires-Python: >=3.7
License-File: LICENSE
Requires-Dist: numpy
